timeslicer/__init__.py
timeslicer/__main__.py
timeslicer/timeslicer.py
timeslicer-1.3.0.dist-info/LICENSE.txt
timeslicer-1.3.0.dist-info/METADATA
timeslicer-1.3.0.dist-info/WHEEL
timeslicer-1.3.0.dist-info/top_level.txt
timeslicer-1.3.0.dist-info/RECORD
