Metadata-Version: 2.1
Name: timeslicer
Version: 1.3.0
Summary: Package for creating timeslice images from time lapses
Home-page: https://github.com/nramkissoon/Time-Slice
Author: Nicholas Ramkissoon
License: UNKNOWN
Platform: UNKNOWN
Classifier: Intended Audience :: Developers
Classifier: Programming Language :: Python :: 3
Classifier: License :: OSI Approved :: MIT License
Classifier: Operating System :: OS Independent
Requires-Python: >=3
